s3tree/__init__.py
s3tree/main.py
s3_tree-0.1.0.dist-info/LICENSE
s3_tree-0.1.0.dist-info/METADATA
s3_tree-0.1.0.dist-info/WHEEL
s3_tree-0.1.0.dist-info/entry_points.txt
s3_tree-0.1.0.dist-info/top_level.txt
s3_tree-0.1.0.dist-info/RECORD
