Metadata-Version: 2.1
Name: s3-tree
Version: 0.1.0
Summary: list s3 objects in tree-like format.
Home-page: https://bitbucket.org/rednap/s3-tree
Author: Andy Klier
Author-email: andyklier@gmail.com
License: UNKNOWN
Platform: UNKNOWN
Classifier: Programming Language :: Python :: 3
Classifier: License :: OSI Approved :: MIT License
Classifier: Operating System :: OS Independent
